.gitignore
README.rst
buildout.cfg
setup.py
docs/HISTORY.rst
experimental/__init__.py
experimental.broken.egg-info/PKG-INFO
experimental.broken.egg-info/SOURCES.txt
experimental.broken.egg-info/dependency_links.txt
experimental.broken.egg-info/entry_points.txt
experimental.broken.egg-info/namespace_packages.txt
experimental.broken.egg-info/not-zip-safe
experimental.broken.egg-info/requires.txt
experimental.broken.egg-info/top_level.txt
experimental/broken/__init__.py
experimental/broken/broken.txt
experimental/broken/configure.zcml
experimental/broken/interface.py
experimental/broken/interface.txt
experimental/broken/plone_broken.py
experimental/broken/registry.py
experimental/broken/registry.txt
experimental/broken/tests.py