Metadata-Version: 2.1
Name: experimental.broken
Version: 0.7
Summary: Better ZODB handling of broken interfaces and components
Home-page: https://github.com/rpatterson/experimental.broken
Author: Ross Patterson
Author-email: me@rpatterson.net
License: ZPL
Platform: UNKNOWN
Classifier: Programming Language :: Python
Classifier: Topic :: Software Development :: Libraries :: Python Modules
Provides-Extra: test
Provides-Extra: registry
Provides-Extra: zcml
